agent_framework_bedrock/__init__.py
agent_framework_bedrock/_chat_client.py
agent_framework_bedrock-1.0.0b260130.dist-info/METADATA
agent_framework_bedrock-1.0.0b260130.dist-info/WHEEL
agent_framework_bedrock-1.0.0b260130.dist-info/licenses/LICENSE
agent_framework_bedrock-1.0.0b260130.dist-info/RECORD
