Metadata-Version: 2.4
Name: agent-framework-bedrock
Version: 1.0.0b260130
Summary: Amazon Bedrock integration for Microsoft Agent Framework.
Project-URL: homepage, https://aka.ms/agent-framework
Project-URL: source, https://github.com/microsoft/agent-framework/tree/main/python
Project-URL: release_notes, https://github.com/microsoft/agent-framework/releases?q=tag%3Apython-1&expanded=true
Project-URL: issues, https://github.com/microsoft/agent-framework/issues
Author-email: Microsoft <af-support@microsoft.com>
License-File: LICENSE
Classifier: Development Status :: 4 - Beta
Classifier: Intended Audience :: Developers
Classifier: License :: OSI Approved :: MIT License
Classifier: Programming Language :: Python :: 3
Classifier: Programming Language :: Python :: 3.10
Classifier: Programming Language :: Python :: 3.11
Classifier: Programming Language :: Python :: 3.12
Classifier: Programming Language :: Python :: 3.13
Classifier: Programming Language :: Python :: 3.14
Classifier: Typing :: Typed
Requires-Python: >=3.10
Requires-Dist: agent-framework-core
Requires-Dist: boto3<2.0.0,>=1.35.0
Requires-Dist: botocore<2.0.0,>=1.35.0
